docker/.env.docker
docker/__init__.py
docker/compose.yml
flou/__init__.py
flou/cli.py
flou/conf.py
flou/exceptions.py
flou/registry.py
flou/utils.py
flou/api/__init__.py
flou/api/dependencies.py
flou/api/main.py
flou/api/models.py
flou/api/router.py
flou/api/schemas.py
flou/app/app.py
flou/database/__init__.py
flou/database/base.py
flou/database/models.py
flou/database/sqlite.py
flou/database/utils.py
flou/engine/__init__.py
flou/engine/base.py
flou/engine/celery.py
flou/engine/dummy.py
flou/engine/models.py
flou/engine/router.py
flou/engine/schemas.py
flou/experiments/__init__.py
flou/experiments/models.py
flou/experiments/router.py
flou/experiments/schemas.py
flou/ltm/__init__.py
flou/ltm/ltm.py
flou/ltm/models.py
migrations/env.py
migrations/versions/2024_10_25_1016-f55cc59c874c_.py
migrations/versions/2024_11_04_1822-bb20ac30a018_.py
migrations/versions/2024_11_07_1418-90f041e667a5_.py
migrations/versions/2024_11_07_1418-a3563fe36f94_.py
migrations/versions/2024_11_14_1125-74105a812f10_.py
flou-0.3.0.dev3.dist-info/METADATA
flou-0.3.0.dev3.dist-info/WHEEL
flou-0.3.0.dev3.dist-info/entry_points.txt
flou-0.3.0.dev3.dist-info/top_level.txt
flou-0.3.0.dev3.dist-info/RECORD
