Metadata-Version: 2.1
Name: flou
Version: 0.3.0.dev3
Summary: The framework for LLM-powered apps
Author-email: Iván Raskovsky <raskovsky+flou@gmail.com>
Project-URL: Homepage, https://flou.ai
Project-URL: Documentation, https://flou.ai/
Project-URL: Repository, https://github.com/flou-ai/flou.git
Project-URL: Issues, https://github.com/flou-ai/flou/issues
Project-URL: Changelog, https://flou.ai/documentation/changelog
Requires-Dist: fastapi[standard]
Requires-Dist: uvicorn
Requires-Dist: pydantic-settings
Requires-Dist: celery
Requires-Dist: python-dotenv
Requires-Dist: pytest
Requires-Dist: jsonpatch
Requires-Dist: redis
Requires-Dist: typer
Requires-Dist: websockets
Requires-Dist: broadcaster[redis]
Requires-Dist: parse
Requires-Dist: watchdog
Requires-Dist: sqlalchemy[asyncio]
Requires-Dist: alembic
Requires-Dist: alembic_utils
Requires-Dist: psycopg
